{
    "name": "Опал і Гранат",
    "icon": "gtceu:opal_gem",
    "category": "tfc:tfg_ores",
    "read_by_default": true,
    "pages": [
        {
            "type": "patchouli:text",
            "text": "Рідкість: 220$(br)Щільність: 0.35$(br)Тип: Дискова вена(br)Y: -64 - 62$(br)Розмір: 26$(br)Висота: 6$(br2)Типи каменю: Ріоліт, Базальт, Андезит, Дацит, Граніт, Діорит, Габро$(br2)Індикатор: Родючий Аметист"
        },
        {
            "type": "patchouli:multiblock",
            "name": "Опал",
            "multiblock": {
                "mapping": {
                    "0": "#forge:ores/opal"
                },
                "pattern": [
                    [
                        "0"
                    ],
                    [
                        " "
                    ]
                ]
            },
            "enable_visualize": false,
            "text": "Відсоток: 55%$(br)Формула: (SiO₂)"
        },
        {
            "type": "patchouli:multiblock",
            "name": "Аметист",
            "multiblock": {
                "mapping": {
                    "0": "#forge:ores/amethyst"
                },
                "pattern": [
                    [
                        "0"
                    ],
                    [
                        " "
                    ]
                ]
            },
            "enable_visualize": false,
            "text": "Відсоток: 25%$(br)Джерело: Заліза$(br)Формула: (SiO₂)₄Fe"
        },
        {
            "type": "patchouli:multiblock",
            "name": "Червоний гранат",
            "multiblock": {
                "mapping": {
                    "0": "#forge:ores/red_garnet"
                },
                "pattern": [
                    [
                        "0"
                    ],
                    [
                        " "
                    ]
                ]
            },
            "enable_visualize": false,
            "text": "Відсоток: 5%$(br)Source of: Піроп, Алмадін, Спесартін"
        },
        {
            "type": "patchouli:multiblock",
            "name": "Жовтий гранат",
            "multiblock": {
                "mapping": {
                    "0": "#forge:ores/yellow_garnet"
                },
                "pattern": [
                    [
                        "0"
                    ],
                    [
                        " "
                    ]
                ]
            },
            "enable_visualize": false,
            "text": "Відсоток: 15%$(br)Джерело: Andradite, Grossular, Uvarovite"
        }
    ]
}