{
	"name": "",
	"category": "",
	"icon": "",
	"pages": [
		{
			"type": "",
			"text": ""
		},
		{
			"type": "",
			"title": "Antre Luxuriante",
			"images": [
				""
			],
			"border": "",
			"text": ""
		},
		{
			"type": "",
			"title": "Cavernes Délabrés",
			"images": [
				""
			],
			"border": "",
			"text": ""
		},
		{
			"type": "",
			"title": "Repaire Toilé",
			"images": [
				""
			],
			"border": "",
			"text": ""
		},
		{
			"type": "",
			"title": "Forêt de Cendres",
			"images": [
				""
			],
			"border": "",
			"text": ""
		},
		{
			"type": "",
			"title": "Banquise de Lave",
			"images": [
				""
			],
			"border": "",
			"text": ""
		},
		{
			"type": "",
			"title": "Deltas de Basalte",
			"images": [
				""
			],
			"border": "",
			"text": ""
		},
		{
			"type": "",
			"title": "Grottes Profondes",
			"images": [
				""
			],
			"border": "",
			"text": ""
		}
	],
	"read_by_default": ""
}