{
    "material.tfg.latex": "Latex",
    "material.tfg.vulcanized_latex": "Vulcanized Latex",
    "material.tfg.fluix": "Fluix",
    "material.tfg.conifer_pitch": "Conifer Pitch",

    "material.gtceu.lactose": "Lactose",

    "material.tfg.gabbro": "Gabbro",
    "material.tfg.shale": "Shale",
    "material.tfg.claystone": "Claystone",
    "material.tfg.limestone": "Limestone",
    "material.tfg.conglomerate": "Conglomerate",
    "material.tfg.dolomite": "Dolomite",
    "material.tfg.chert": "Chert",
    "material.tfg.rhyolite": "Rhyolite",
    "material.tfg.dacite": "Dacite",
    "material.tfg.slate": "Slate",
    "material.tfg.phyllite": "Phyllite",
    "material.tfg.schist": "Schist",
    "material.tfg.gneiss": "Gneiss",
    "material.tfg.chalk": "Chalk",

    "material.gtceu.thermochemically_treated_hardwood": "Thermochemically Treated Hardwood",
    "material.gtceu.hardwood": "Hardwood"
}