{
  "__credits__": "This vein was automatically generated by OresToFieldGuide.",
  "type": "tfc:pipe_vein",
  "config": {
    "height": 33,
    "radius": 8,
    "min_skew": 5,
    "max_skew": 15,
    "min_slant": 2,
    "max_slant": 5,
    "sign": 0.5,
    "rarity": 10,
    "density": 0.22,
    "min_y": 80,
    "max_y": 140,
    "random_name": "beneath_aluminium",
    "project": false,
    "project_offset": false,
    "near_lava": false,
    "biomes": "#tfg:nether/is_tar_pools",
    "blocks": [
      {
        "replace": [
          "tfc:rock/raw/granite"
        ],
        "with": [
          {
            "block": "gtceu:granite_alunite_ore",
            "weight": 5
          },
          {
            "block": "gtceu:raw_alunite_block",
            "weight": 1
          },
          {
            "block": "gtceu:granite_zeolite_ore",
            "weight": 3
          },
          {
            "block": "gtceu:granite_barite_ore",
            "weight": 2
          }
        ]
      },
      {
        "replace": [
          "tfc:rock/raw/diorite"
        ],
        "with": [
          {
            "block": "gtceu:diorite_alunite_ore",
            "weight": 5
          },
          {
            "block": "gtceu:raw_alunite_block",
            "weight": 1
          },
          {
            "block": "gtceu:diorite_zeolite_ore",
            "weight": 3
          },
          {
            "block": "gtceu:diorite_barite_ore",
            "weight": 2
          }
        ]
      },
      {
        "replace": [
          "tfc:rock/raw/gabbro"
        ],
        "with": [
          {
            "block": "gtceu:gabbro_alunite_ore",
            "weight": 5
          },
          {
            "block": "gtceu:raw_alunite_block",
            "weight": 1
          },
          {
            "block": "gtceu:gabbro_zeolite_ore",
            "weight": 3
          },
          {
            "block": "gtceu:gabbro_barite_ore",
            "weight": 2
          }
        ]
      },
      {
        "replace": [
          "tfc:rock/raw/rhyolite"
        ],
        "with": [
          {
            "block": "gtceu:rhyolite_alunite_ore",
            "weight": 5
          },
          {
            "block": "gtceu:raw_alunite_block",
            "weight": 1
          },
          {
            "block": "gtceu:rhyolite_zeolite_ore",
            "weight": 3
          },
          {
            "block": "gtceu:rhyolite_barite_ore",
            "weight": 2
          }
        ]
      },
      {
        "replace": [
          "tfc:rock/raw/basalt",
          "minecraft:basalt"
        ],
        "with": [
          {
            "block": "gtceu:basalt_alunite_ore",
            "weight": 5
          },
          {
            "block": "gtceu:raw_alunite_block",
            "weight": 1
          },
          {
            "block": "gtceu:basalt_zeolite_ore",
            "weight": 3
          },
          {
            "block": "gtceu:basalt_barite_ore",
            "weight": 2
          }
        ]
      },
      {
        "replace": [
          "tfc:rock/raw/andesite"
        ],
        "with": [
          {
            "block": "gtceu:andesite_alunite_ore",
            "weight": 5
          },
          {
            "block": "gtceu:raw_alunite_block",
            "weight": 1
          },
          {
            "block": "gtceu:andesite_zeolite_ore",
            "weight": 3
          },
          {
            "block": "gtceu:andesite_barite_ore",
            "weight": 2
          }
        ]
      },
      {
        "replace": [
          "tfc:rock/raw/dacite"
        ],
        "with": [
          {
            "block": "gtceu:dacite_alunite_ore",
            "weight": 5
          },
          {
            "block": "gtceu:raw_alunite_block",
            "weight": 1
          },
          {
            "block": "gtceu:dacite_zeolite_ore",
            "weight": 3
          },
          {
            "block": "gtceu:dacite_barite_ore",
            "weight": 2
          }
        ]
      },
      {
        "replace": [
          "tfc:rock/raw/shale"
        ],
        "with": [
          {
            "block": "gtceu:shale_alunite_ore",
            "weight": 5
          },
          {
            "block": "gtceu:raw_alunite_block",
            "weight": 1
          },
          {
            "block": "gtceu:shale_zeolite_ore",
            "weight": 3
          },
          {
            "block": "gtceu:shale_barite_ore",
            "weight": 2
          }
        ]
      },
      {
        "replace": [
          "tfc:rock/raw/claystone"
        ],
        "with": [
          {
            "block": "gtceu:claystone_alunite_ore",
            "weight": 5
          },
          {
            "block": "gtceu:raw_alunite_block",
            "weight": 1
          },
          {
            "block": "gtceu:claystone_zeolite_ore",
            "weight": 3
          },
          {
            "block": "gtceu:claystone_barite_ore",
            "weight": 2
          }
        ]
      },
      {
        "replace": [
          "tfc:rock/raw/limestone"
        ],
        "with": [
          {
            "block": "gtceu:limestone_alunite_ore",
            "weight": 5
          },
          {
            "block": "gtceu:raw_alunite_block",
            "weight": 1
          },
          {
            "block": "gtceu:limestone_zeolite_ore",
            "weight": 3
          },
          {
            "block": "gtceu:limestone_barite_ore",
            "weight": 2
          }
        ]
      },
      {
        "replace": [
          "tfc:rock/raw/conglomerate"
        ],
        "with": [
          {
            "block": "gtceu:conglomerate_alunite_ore",
            "weight": 5
          },
          {
            "block": "gtceu:raw_alunite_block",
            "weight": 1
          },
          {
            "block": "gtceu:conglomerate_zeolite_ore",
            "weight": 3
          },
          {
            "block": "gtceu:conglomerate_barite_ore",
            "weight": 2
          }
        ]
      },
      {
        "replace": [
          "tfc:rock/raw/dolomite"
        ],
        "with": [
          {
            "block": "gtceu:dolomite_alunite_ore",
            "weight": 5
          },
          {
            "block": "gtceu:raw_alunite_block",
            "weight": 1
          },
          {
            "block": "gtceu:dolomite_zeolite_ore",
            "weight": 3
          },
          {
            "block": "gtceu:dolomite_barite_ore",
            "weight": 2
          }
        ]
      },
      {
        "replace": [
          "tfc:rock/raw/chert"
        ],
        "with": [
          {
            "block": "gtceu:chert_alunite_ore",
            "weight": 5
          },
          {
            "block": "gtceu:raw_alunite_block",
            "weight": 1
          },
          {
            "block": "gtceu:chert_zeolite_ore",
            "weight": 3
          },
          {
            "block": "gtceu:chert_barite_ore",
            "weight": 2
          }
        ]
      },
      {
        "replace": [
          "tfc:rock/raw/chalk"
        ],
        "with": [
          {
            "block": "gtceu:chalk_alunite_ore",
            "weight": 5
          },
          {
            "block": "gtceu:raw_alunite_block",
            "weight": 1
          },
          {
            "block": "gtceu:chalk_zeolite_ore",
            "weight": 3
          },
          {
            "block": "gtceu:chalk_barite_ore",
            "weight": 2
          }
        ]
      },
      {
        "replace": [
          "minecraft:tuff"
        ],
        "with": [
          {
            "block": "gtceu:tuff_alunite_ore",
            "weight": 5
          },
          {
            "block": "gtceu:raw_alunite_block",
            "weight": 1
          },
          {
            "block": "gtceu:tuff_zeolite_ore",
            "weight": 3
          },
          {
            "block": "gtceu:tuff_barite_ore",
            "weight": 2
          }
        ]
      },
      {
        "replace": [
          "tfc:rock/raw/quartzite"
        ],
        "with": [
          {
            "block": "gtceu:quartzite_alunite_ore",
            "weight": 5
          },
          {
            "block": "gtceu:raw_alunite_block",
            "weight": 1
          },
          {
            "block": "gtceu:quartzite_zeolite_ore",
            "weight": 3
          },
          {
            "block": "gtceu:quartzite_barite_ore",
            "weight": 2
          }
        ]
      },
      {
        "replace": [
          "tfc:rock/raw/slate"
        ],
        "with": [
          {
            "block": "gtceu:slate_alunite_ore",
            "weight": 5
          },
          {
            "block": "gtceu:raw_alunite_block",
            "weight": 1
          },
          {
            "block": "gtceu:slate_zeolite_ore",
            "weight": 3
          },
          {
            "block": "gtceu:slate_barite_ore",
            "weight": 2
          }
        ]
      },
      {
        "replace": [
          "tfc:rock/raw/phyllite"
        ],
        "with": [
          {
            "block": "gtceu:phyllite_alunite_ore",
            "weight": 5
          },
          {
            "block": "gtceu:raw_alunite_block",
            "weight": 1
          },
          {
            "block": "gtceu:phyllite_zeolite_ore",
            "weight": 3
          },
          {
            "block": "gtceu:phyllite_barite_ore",
            "weight": 2
          }
        ]
      },
      {
        "replace": [
          "tfc:rock/raw/schist"
        ],
        "with": [
          {
            "block": "gtceu:schist_alunite_ore",
            "weight": 5
          },
          {
            "block": "gtceu:raw_alunite_block",
            "weight": 1
          },
          {
            "block": "gtceu:schist_zeolite_ore",
            "weight": 3
          },
          {
            "block": "gtceu:schist_barite_ore",
            "weight": 2
          }
        ]
      },
      {
        "replace": [
          "tfc:rock/raw/gneiss"
        ],
        "with": [
          {
            "block": "gtceu:gneiss_alunite_ore",
            "weight": 5
          },
          {
            "block": "gtceu:raw_alunite_block",
            "weight": 1
          },
          {
            "block": "gtceu:gneiss_zeolite_ore",
            "weight": 3
          },
          {
            "block": "gtceu:gneiss_barite_ore",
            "weight": 2
          }
        ]
      },
      {
        "replace": [
          "tfc:rock/raw/marble"
        ],
        "with": [
          {
            "block": "gtceu:marble_alunite_ore",
            "weight": 5
          },
          {
            "block": "gtceu:raw_alunite_block",
            "weight": 1
          },
          {
            "block": "gtceu:marble_zeolite_ore",
            "weight": 3
          },
          {
            "block": "gtceu:marble_barite_ore",
            "weight": 2
          }
        ]
      },
      {
        "replace": [
          "minecraft:deepslate"
        ],
        "with": [
          {
            "block": "gtceu:deepslate_alunite_ore",
            "weight": 5
          },
          {
            "block": "gtceu:raw_alunite_block",
            "weight": 1
          },
          {
            "block": "gtceu:deepslate_zeolite_ore",
            "weight": 3
          },
          {
            "block": "gtceu:deepslate_barite_ore",
            "weight": 2
          }
        ]
      },
      {
        "replace": [
          "minecraft:blackstone",
          "minecraft:magma_block"
        ],
        "with": [
          {
            "block": "gtceu:pyroxenite_alunite_ore",
            "weight": 5
          },
          {
            "block": "gtceu:raw_alunite_block",
            "weight": 1
          },
          {
            "block": "gtceu:pyroxenite_zeolite_ore",
            "weight": 3
          },
          {
            "block": "gtceu:pyroxenite_barite_ore",
            "weight": 2
          }
        ]
      },
      {
        "replace": [
          "minecraft:dripstone_block"
        ],
        "with": [
          {
            "block": "gtceu:dripstone_alunite_ore",
            "weight": 5
          },
          {
            "block": "gtceu:raw_alunite_block",
            "weight": 1
          },
          {
            "block": "gtceu:dripstone_zeolite_ore",
            "weight": 3
          },
          {
            "block": "gtceu:dripstone_barite_ore",
            "weight": 2
          }
        ]
      }
    ],
    "indicator": {
      "rarity": 22,
      "depth": 30,
      "underground_rarity": 40,
      "underground_count": 200,
      "blocks": [
        {
          "block": "gtceu:alunite_indicator",
          "weight": 5
        },
        {
          "block": "gtceu:zeolite_indicator",
          "weight": 3
        },
        {
          "block": "gtceu:barite_indicator",
          "weight": 2
        }
      ]
    }
  }
}