{
	"__comment__": "This file was automatically created by mcresources",
	"name": "原始合金",
	"category": "tfc:getting_started",
	"icon": "tfc:ceramic/ingot_mold{tank:{\"Amount\":100,\"FluidName\":\"tfc:metal/bronze\"}}",
	"pages": [
		{
			"type": "patchouli:text",
			"text": "$(thing)合金$()是由兩種以上的金屬混合而成的強化金屬。遊戲初期銅很實用，但要發展到下一階段文明，就必須想方設法做出 $(thing)青銅$()。熔化不同 $(thing)金属$() 使其混合，所有成分處於特定比例就可做出相應的合金。"
		},
		{
			"type": "patchouli:text",
			"text": "$(thing)小缸$()是遊戲初期唯一可以製作合金的手段。製作合金的步驟與$(l:getting_started/finding_ores#casting)鑄造$()相似，區別在於小缸內放置多種不同金屬而非單獨放入銅。小缸內的金屬處於特定比例內，熔化所得的金屬就會轉化為合金。"
		},
		{
			"type": "patchouli:text",
			"text": "例如要合成 1000 mB 的$(thing)青銅$()（右側所示），需要加入 700~800 mB 的$(thing)銅$()以及 200~300 mB 的$(thing)錫$()。$(br2)接下來幾頁展示了三種不同的銅合金。每種銅合金都可以做成工具、$(l:mechanics/armor)盔甲$()和其他金屬物品，但耐久度、效率和傷害有些許差異。"
		},
		{
			"type": "patchouli:spotlight",
			"item": "gtceu:bronze_ingot",
			"title": "青銅",
			"link_recipes": false,
			"text": "$(br)$(bold)條件：$()$(br)$(li)70 - 80 %：$(thing)銅$()$(li)20 - 30 %：$(thing)錫$()$(br2)"
		},
		{
			"type": "patchouli:spotlight",
			"item": "gtceu:bismuth_bronze_ingot",
			"title": "鉍青銅",
			"link_recipes": false,
			"text": "$(br)$(bold)條件：$()$(br)$(li)20 - 30 %：$(thing)鋅$()$(li)50 - 65 %：$(thing)銅$()$(li)10 - 20 %：$(thing)鉍$()$(br2)"
		},
		{
			"type": "patchouli:spotlight",
			"item": "gtceu:black_bronze_ingot",
			"title": "黑青銅",
			"link_recipes": false,
			"text": "$(br)$(bold)條件：$()$(br)$(li)50 - 70 %：$(thing)銅$()$(li)10 - 25 %：$(thing)銀$()$(li)10 - 25 %：$(thing)金$()$(br2)"
		},
		{
			"type": "patchouli:text",
			"text": "還有些不適合製作為工具的合金，像是 $(thing)黃銅$() 、 $(thing)玫瑰金$()和$(thing)紋銀$()。$(br2)$(thing)黃銅$()主要用來製作各種小零件，如$(l:mechanics/mechanical_power)機械動力$()。$(br2)$(thing)玫瑰金$()和$(thing)紋銀$()則是熔煉$(l:mechanics/steel#red_steel)紅鋼$()和$(l:mechanics/steel#blue_steel)藍鋼$()時的必要原料。",
			"title": "功能合金"
		},
		{
			"type": "patchouli:spotlight",
			"anchor": "brass",
			"item": "create:brass_ingot",
			"title": "黃銅",
			"link_recipes": false,
			"text": "$(br)$(bold)條件：$()$(br)$(li)70 - 80 %：$(thing)銅$()$(li)20 - 30 %：$(thing)鋅$()$(br2)"
		},
		{
			"type": "patchouli:spotlight",
			"item": "gtceu:rose_gold_ingot",
			"title": "熔融玫瑰金",
			"link_recipes": false,
			"text": "$(br)$(bold)條件：$()$(br)$(li)70 - 80 %：$(thing)銅$()$(li)20 - 30 %：$(thing)金$()$(br2)"
		},
		{
			"type": "patchouli:spotlight",
			"item": "gtceu:sterling_silver_ingot",
			"title": "紋銀",
			"link_recipes": false,
			"text": "$(br)$(bold)條件:$()$(br)$(li)20 - 40 % : $(thing)銅$()$(li)60 - 80 % : $(thing)銀$()$(br2)"
		}
	],
	"read_by_default": true,
	"sortnum": 5,
	"extra_recipe_mappings": {
		"gtceu:bronze_ingot": 3,
		"gtceu:bismuth_bronze_ingot": 4,
		"gtceu:black_bronze_ingot": 5,
		"create:brass_ingot": 7
	}
}