{"variants":{"age=0,stick=false":{"model":"tfg:block/crop/cucumber_bottom_0"},"age=1,stick=false":{"model":"tfg:block/crop/cucumber_bottom_1"},"age=0,stick=true,part=bottom":{"model":"tfg:block/crop/cucumber_bottom_stick_0"},"age=1,stick=true,part=bottom":{"model":"tfg:block/crop/cucumber_bottom_stick_1"},"age=0,stick=true,part=top":{"model":"tfc:block/crop/stick"},"age=1,stick=true,part=top":{"model":"tfc:block/crop/stick"},"age=2,part=bottom":{"model":"tfg:block/crop/cucumber_bottom_stick_2"},"age=3,part=bottom":{"model":"tfg:block/crop/cucumber_bottom_stick_3"},"age=4,part=bottom":{"model":"tfg:block/crop/cucumber_bottom_stick_4"},"age=5,part=bottom":{"model":"tfg:block/crop/cucumber_bottom_stick_5"},"age=2,part=top":{"model":"tfg:block/crop/cucumber_top_stick_2"},"age=3,part=top":{"model":"tfg:block/crop/cucumber_top_stick_3"},"age=4,part=top":{"model":"tfg:block/crop/cucumber_top_stick_4"},"age=5,part=top":{"model":"tfg:block/crop/cucumber_top_stick_5"}}}